rastermap/__init__.py
rastermap/__main__.py
rastermap/cluster.py
rastermap/io.py
rastermap/rastermap.py
rastermap/sort.py
rastermap/svd.py
rastermap/upsample.py
rastermap/utils.py
rastermap/gui/colormaps.py
rastermap/gui/gui.py
rastermap/gui/guiparts.py
rastermap/gui/io.py
rastermap/gui/menus.py
rastermap/gui/run.py
rastermap/gui/views.py
rastermap-0.9.5.dist-info/LICENSE
rastermap-0.9.5.dist-info/METADATA
rastermap-0.9.5.dist-info/WHEEL
rastermap-0.9.5.dist-info/top_level.txt
rastermap-0.9.5.dist-info/RECORD
