Metadata-Version: 2.1
Name: rastermap
Version: 0.9.5
Summary: Unsupervised clustering algorithm for 2D data (neurons by time)
Home-page: https://github.com/MouseLand/rastermap
Author: Marius Pachitariu and Carsen Stringer
Author-email: carsen.stringer@gmail.com
Classifier: Programming Language :: Python :: 3
Classifier: License :: OSI Approved :: GNU General Public License v3 (GPLv3)
Classifier: Operating System :: OS Independent
License-File: LICENSE
Requires-Dist: numpy >=1.24.0
Requires-Dist: scipy
Requires-Dist: scikit-learn
Requires-Dist: numba >=0.57.0
Requires-Dist: natsort
Requires-Dist: tqdm
Provides-Extra: gui
Requires-Dist: pyqtgraph >=0.11.0rc0 ; extra == 'gui'
Requires-Dist: pyqt6 ; extra == 'gui'
Requires-Dist: pyqt6.sip ; extra == 'gui'
Requires-Dist: qtpy ; extra == 'gui'
Requires-Dist: superqt ; extra == 'gui'
